<annotation>
	<folder>phostr</folder>
	<filename>20190607_133926.jpg</filename>
	<path>C:\Users\pipir\Desktop\phostr\20190607_133926.jpg</path>
	<source>
		<database>Unknown</database>
	</source>
	<size>
		<width>5312</width>
		<height>2988</height>
		<depth>3</depth>
	</size>
	<segmented>0</segmented>
	<object>
		<name>Cultural lecture hall</name>
		<pose>Unspecified</pose>
		<truncated>0</truncated>
		<difficult>0</difficult>
		<bndbox>
			<xmin>1837</xmin>
			<ymin>1194</ymin>
			<xmax>2519</xmax>
			<ymax>1626</ymax>
		</bndbox>
	</object>
	<object>
		<name>Engineering College Building 3</name>
		<pose>Unspecified</pose>
		<truncated>0</truncated>
		<difficult>0</difficult>
		<bndbox>
			<xmin>4623</xmin>
			<ymin>1226</ymin>
			<xmax>5269</xmax>
			<ymax>1697</ymax>
		</bndbox>
	</object>
	<object>
		<name>College of Natural Science</name>
		<pose>Unspecified</pose>
		<truncated>0</truncated>
		<difficult>0</difficult>
		<bndbox>
			<xmin>1816</xmin>
			<ymin>972</ymin>
			<xmax>2273</xmax>
			<ymax>1104</ymax>
		</bndbox>
	</object>
</annotation>
