<annotation>
	<folder>train</folder>
	<filename>20190608_080640(0).jpg</filename>
	<path>C:\Users\JUWON\Desktop\train\20190608_080640(0).jpg</path>
	<source>
		<database>Unknown</database>
	</source>
	<size>
		<width>504</width>
		<height>378</height>
		<depth>3</depth>
	</size>
	<segmented>0</segmented>
	<object>
		<name>College of Social Sciences</name>
		<pose>Unspecified</pose>
		<truncated>0</truncated>
		<difficult>0</difficult>
		<bndbox>
			<xmin>94</xmin>
			<ymin>22</ymin>
			<xmax>503</xmax>
			<ymax>304</ymax>
		</bndbox>
	</object>
	<object>
		<name>College of Social Sciences</name>
		<pose>Unspecified</pose>
		<truncated>1</truncated>
		<difficult>0</difficult>
		<bndbox>
			<xmin>137</xmin>
			<ymin>143</ymin>
			<xmax>504</xmax>
			<ymax>312</ymax>
		</bndbox>
	</object>
	<object>
		<name>College of Social Sciences</name>
		<pose>Unspecified</pose>
		<truncated>0</truncated>
		<difficult>0</difficult>
		<bndbox>
			<xmin>186</xmin>
			<ymin>49</ymin>
			<xmax>476</xmax>
			<ymax>135</ymax>
		</bndbox>
	</object>
</annotation>
