<annotation>
	<folder>qwer</folder>
	<filename>20190608_074907.jpg</filename>
	<path>C:\Users\JUWON\Desktop\qwer\20190608_074907.jpg</path>
	<source>
		<database>Unknown</database>
	</source>
	<size>
		<width>4032</width>
		<height>3024</height>
		<depth>3</depth>
	</size>
	<segmented>0</segmented>
	<object>
		<name>Main Building of University</name>
		<pose>Unspecified</pose>
		<truncated>0</truncated>
		<difficult>0</difficult>
		<bndbox>
			<xmin>152</xmin>
			<ymin>696</ymin>
			<xmax>4006</xmax>
			<ymax>2403</ymax>
		</bndbox>
	</object>
	<object>
		<name>Main Building of University</name>
		<pose>Unspecified</pose>
		<truncated>0</truncated>
		<difficult>0</difficult>
		<bndbox>
			<xmin>2520</xmin>
			<ymin>1753</ymin>
			<xmax>3954</xmax>
			<ymax>2391</ymax>
		</bndbox>
	</object>
	<object>
		<name>Main Building of University</name>
		<pose>Unspecified</pose>
		<truncated>0</truncated>
		<difficult>0</difficult>
		<bndbox>
			<xmin>1199</xmin>
			<ymin>1126</ymin>
			<xmax>3947</xmax>
			<ymax>1696</ymax>
		</bndbox>
	</object>
</annotation>
