<annotation>
	<folder>qwer</folder>
	<filename>20190608_075401(0).jpg</filename>
	<path>C:\Users\JUWON\Desktop\qwer\20190608_075401(0).jpg</path>
	<source>
		<database>Unknown</database>
	</source>
	<size>
		<width>4032</width>
		<height>3024</height>
		<depth>3</depth>
	</size>
	<segmented>0</segmented>
	<object>
		<name>College of Social Sciences</name>
		<pose>Unspecified</pose>
		<truncated>0</truncated>
		<difficult>0</difficult>
		<bndbox>
			<xmin>238</xmin>
			<ymin>1316</ymin>
			<xmax>3097</xmax>
			<ymax>1957</ymax>
		</bndbox>
	</object>
	<object>
		<name>College of Social Sciences</name>
		<pose>Unspecified</pose>
		<truncated>0</truncated>
		<difficult>0</difficult>
		<bndbox>
			<xmin>765</xmin>
			<ymin>1391</ymin>
			<xmax>3061</xmax>
			<ymax>1760</ymax>
		</bndbox>
	</object>
	<object>
		<name>College of Social Sciences</name>
		<pose>Unspecified</pose>
		<truncated>0</truncated>
		<difficult>0</difficult>
		<bndbox>
			<xmin>1329</xmin>
			<ymin>1407</ymin>
			<xmax>2429</xmax>
			<ymax>1939</ymax>
		</bndbox>
	</object>
	<object>
		<name>College of Social Sciences</name>
		<pose>Unspecified</pose>
		<truncated>0</truncated>
		<difficult>0</difficult>
		<bndbox>
			<xmin>1320</xmin>
			<ymin>1746</ymin>
			<xmax>1658</xmax>
			<ymax>1973</ymax>
		</bndbox>
	</object>
	<object>
		<name>College of Social Sciences</name>
		<pose>Unspecified</pose>
		<truncated>0</truncated>
		<difficult>0</difficult>
		<bndbox>
			<xmin>2761</xmin>
			<ymin>1541</ymin>
			<xmax>2954</xmax>
			<ymax>1607</ymax>
		</bndbox>
	</object>
</annotation>
