<annotation>
	<folder>qwer</folder>
	<filename>20190608_074313.jpg</filename>
	<path>C:\Users\JUWON\Desktop\qwer\20190608_074313.jpg</path>
	<source>
		<database>Unknown</database>
	</source>
	<size>
		<width>4032</width>
		<height>3024</height>
		<depth>3</depth>
	</size>
	<segmented>0</segmented>
	<object>
		<name>Gym</name>
		<pose>Unspecified</pose>
		<truncated>0</truncated>
		<difficult>0</difficult>
		<bndbox>
			<xmin>533</xmin>
			<ymin>385</ymin>
			<xmax>3952</xmax>
			<ymax>1798</ymax>
		</bndbox>
	</object>
</annotation>
