<annotation>
	<folder>Engineering College Building 4</folder>
	<filename>20190319_100143.jpg</filename>
	<path>C:\Users\pipir\Downloads\drive-download-20190512T131245Z-001\Engineering College Building 4\20190319_100143.jpg</path>
	<source>
		<database>Unknown</database>
	</source>
	<size>
		<width>504</width>
		<height>378</height>
		<depth>3</depth>
	</size>
	<segmented>0</segmented>
	<object>
		<name>Engineering College Building 4</name>
		<pose>Unspecified</pose>
		<truncated>0</truncated>
		<difficult>0</difficult>
		<bndbox>
			<xmin>3</xmin>
			<ymin>108</ymin>
			<xmax>496</xmax>
			<ymax>268</ymax>
		</bndbox>
	</object>
	<object>
		<name>Engineering College Building 4</name>
		<pose>Unspecified</pose>
		<truncated>0</truncated>
		<difficult>0</difficult>
		<bndbox>
			<xmin>180</xmin>
			<ymin>134</ymin>
			<xmax>474</xmax>
			<ymax>264</ymax>
		</bndbox>
	</object>
	<object>
		<name>Engineering College Building 4</name>
		<pose>Unspecified</pose>
		<truncated>0</truncated>
		<difficult>0</difficult>
		<bndbox>
			<xmin>10</xmin>
			<ymin>122</ymin>
			<xmax>187</xmax>
			<ymax>259</ymax>
		</bndbox>
	</object>
</annotation>
