<annotation>
	<folder>phostr</folder>
	<filename>20190607_132852.jpg</filename>
	<path>C:\Users\pipir\Desktop\phostr\20190607_132852.jpg</path>
	<source>
		<database>Unknown</database>
	</source>
	<size>
		<width>5312</width>
		<height>2988</height>
		<depth>3</depth>
	</size>
	<segmented>0</segmented>
	<object>
		<name>Cultural lecture hall</name>
		<pose>Unspecified</pose>
		<truncated>0</truncated>
		<difficult>0</difficult>
		<bndbox>
			<xmin>1934</xmin>
			<ymin>1129</ymin>
			<xmax>2537</xmax>
			<ymax>1640</ymax>
		</bndbox>
	</object>
	<object>
		<name>Cultural lecture hall</name>
		<pose>Unspecified</pose>
		<truncated>0</truncated>
		<difficult>0</difficult>
		<bndbox>
			<xmin>1948</xmin>
			<ymin>1147</ymin>
			<xmax>2073</xmax>
			<ymax>1651</ymax>
		</bndbox>
	</object>
</annotation>
